[
  {
    "id": "693634",
    "referralDate": "2022-03-04T10:14:18.372Z",
    "referrer": {
      "name": "Kathlyn O'Connell",
      "jobTitle": "Headteacher",
      "phoneNumber": "07936 005 943",
      "organisation": {
        "name": "Aufderhar - Reichel School",
        "address": {
          "line1": "1 The Avenue",
          "town": "London",
          "postcode": "W9 1ST"
        }
      }
    },
    "teacher": {
      "firstName": "Fatima",
      "lastName": "Kunde",
      "hasAnotherName": "Yes",
      "otherName": "Bobsky",
      "dateOfBirth": "2022-04-24T03:09:31.482Z",
      "hasNationalInsuranceNumber": "Yes",
      "nationalInsuranceNumber": "QQ 12 34 56 C",
      "hasTeacherReferenceNumber": "No",
      "hasQTS": "No",
      "hasEmailAddress": "Yes",
      "emailAddress": "fatima.kunde@gmail.com",
      "hasPhoneNumber": "No",
      "address": {
        "line1": "1 The Walk",
        "town": "Manchester",
        "postcode": "M1 1AG"
      },
      "hasJobStartDate": "No",
      "areTheyStillEmployed": "They’re still employed but they’ve been suspended",
      "jobTitle": "Teacher",
      "doesWorkAtSameOrganisation": "Yes",
      "roleDescriptionMethod": "I’ll upload a job description",
      "roleDescriptionFile": {
        "name": "job-description.pdf",
        "size": "1MB"
      },
      "isTeachingSomewhereElse": "Yes, they’re teaching somewhere else",
      "newOrganisation": {
        "name": "Cronin Group School",
        "address": {
          "line1": "1 The Avenue",
          "town": "Manchester",
          "postcode": "M1 2PK"
        }
      }
    },
    "allegation": {
      "method": "I’ll upload the allegation details",
      "file": {
        "name": "allegation-details.pdf",
        "size": "2MB"
      },
      "hasToldDBS": "Yes, I’ve told DBS"
    },
    "previousAllegations": {
      "hasPreviousAllegations": "Yes",
      "method": "I’ll give details of the previous misconduct",
      "description": "Voluptas commodi possimus accusamus omnis vitae sit. Asperiores ratione quasi rem distinctio illo. Aperiam ratione iusto praesentium nemo ducimus.\n\nQuisquam saepe praesentium provident sequi sequi corporis numquam atque animi. Optio distinctio dolorem perspiciatis porro quod vitae non. Porro explicabo iste ipsum praesentium ab doloremque deleniti. Suscipit necessitatibus voluptatibus ullam tempore.\n\nQuas maiores quis fugit aliquid dicta. Sunt doloremque facere consequuntur reprehenderit. Expedita quia deserunt accusantium sequi explicabo adipisci magni. Beatae fugit porro ab magnam corporis consequuntur ipsam. Sunt ea repellendus occaecati."
    },
    "evidence": {
      "hasEvidence": "Yes",
      "files": [
        {
          "name": "main-investigation.pdf",
          "size": "1MB",
          "category": "Documents of internal investigations and outcomes"
        },
        {
          "name": "police-investigation.pdf",
          "size": "3MB",
          "category": "Police investigations and reports"
        },
        {
          "name": "signed-withness-statements.pdf",
          "size": "2MB",
          "category": "Signed witness statements"
        },
        {
          "name": "cctv-footage.mp4",
          "size": "2MB",
          "category": "File notes concerning conduct, behaviour and attitude"
        }
      ]
    }
  },
  {
    "id": "664132",
    "referralDate": "2022-09-07T02:21:39.216Z",
    "referrer": {
      "name": "Rosemary Moen",
      "jobTitle": "Headteacher",
      "phoneNumber": "07951 105 397",
      "organisation": {
        "name": "Willms - Casper School",
        "address": {
          "line1": "1 The Avenue",
          "town": "London",
          "postcode": "W9 1ST"
        }
      }
    },
    "teacher": {
      "firstName": "Selmer",
      "lastName": "Smitham",
      "hasAnotherName": "I do not know",
      "dateOfBirth": "2022-06-13T07:23:07.406Z",
      "hasNationalInsuranceNumber": "No",
      "hasTeacherReferenceNumber": "Yes",
      "trn": "4567814",
      "hasQTS": "I do not know",
      "hasEmailAddress": "No",
      "hasPhoneNumber": "No",
      "address": {
        "line1": "1 The Walk",
        "town": "Manchester",
        "postcode": "M1 1AG"
      },
      "hasJobStartDate": "No",
      "areTheyStillEmployed": "They’re still employed but they’ve been suspended",
      "jobTitle": "Teaching assistant",
      "doesWorkAtSameOrganisation": "Yes",
      "roleDescriptionMethod": "I’ll upload a job description",
      "roleDescriptionFile": {
        "name": "job-description.pdf",
        "size": "1MB"
      },
      "isTeachingSomewhereElse": "No, they’re not teaching somewhere else"
    },
    "allegation": {
      "method": "I’ll upload the allegation details",
      "file": {
        "name": "allegation-details.pdf",
        "size": "2MB"
      },
      "hasToldDBS": "Yes, I’ve told DBS"
    },
    "previousAllegations": {
      "hasPreviousAllegations": "Yes",
      "method": "I’ll upload the previous misconduct details",
      "file": {
        "name": "previous-misconduct-details.pdf",
        "size": "2MB"
      }
    },
    "evidence": {
      "hasEvidence": "Yes",
      "files": [
        {
          "name": "main-investigation.pdf",
          "size": "1MB",
          "category": "Documents of internal investigations and outcomes"
        },
        {
          "name": "police-investigation.pdf",
          "size": "3MB",
          "category": "Police investigations and reports"
        },
        {
          "name": "signed-withness-statements.pdf",
          "size": "2MB",
          "category": "Signed witness statements"
        },
        {
          "name": "cctv-footage.mp4",
          "size": "2MB",
          "category": "File notes concerning conduct, behaviour and attitude"
        }
      ]
    }
  },
  {
    "id": "891979",
    "referralDate": "2022-11-06T04:25:04.435Z",
    "referrer": {
      "name": "Fausto Jakubowski",
      "jobTitle": "Headteacher",
      "phoneNumber": "07994 434 572",
      "organisation": {
        "name": "Murazik and Sons School",
        "address": {
          "line1": "1 The Avenue",
          "town": "London",
          "postcode": "W9 1ST"
        }
      }
    },
    "teacher": {
      "firstName": "Anderson",
      "lastName": "Kilback",
      "hasAnotherName": "I do not know",
      "dateOfBirth": "2022-05-12T05:11:26.436Z",
      "hasNationalInsuranceNumber": "Yes",
      "nationalInsuranceNumber": "QQ 12 34 56 C",
      "hasTeacherReferenceNumber": "Yes",
      "trn": "4567814",
      "hasQTS": "I do not know",
      "hasEmailAddress": "Yes",
      "emailAddress": "anderson.kilback@gmail.com",
      "hasPhoneNumber": "No",
      "address": {
        "line1": "1 The Walk",
        "town": "Manchester",
        "postcode": "M1 1AG"
      },
      "hasJobStartDate": "No",
      "areTheyStillEmployed": "No, they’ve left the organisation",
      "jobEndDate": "2022-09-25T00:02:01.105Z",
      "jobEndReason": "Dismissed",
      "jobTitle": "Headteacher",
      "doesWorkAtSameOrganisation": "Yes",
      "roleDescriptionMethod": "I’ll describe their main duties",
      "isTeachingSomewhereElse": "Yes, they’re teaching somewhere else",
      "newOrganisation": {
        "name": "Hayes - Douglas School",
        "address": {
          "line1": "1 The Avenue",
          "town": "Manchester",
          "postcode": "M1 2PK"
        }
      }
    },
    "allegation": {
      "method": "I’ll do this later",
      "hasToldDBS": "Yes, I’ve told DBS"
    },
    "previousAllegations": {
      "hasPreviousAllegations": "Yes",
      "method": "I’ll give details of the previous misconduct",
      "description": "Cum iure ducimus magnam laborum a cum sed. Ducimus quae dolorem fugiat voluptatibus debitis ullam illo. Totam praesentium eos sunt debitis beatae. Libero sit corporis maxime amet distinctio sed.\n\nMinus nostrum dicta magni consequatur fuga. Inventore minus tenetur vitae possimus quidem nihil earum. Maiores cum inventore repellendus magnam.\n\nAd assumenda tenetur dolorem ullam quo eveniet. Debitis soluta explicabo dicta incidunt ratione aperiam alias. Dolorem saepe sapiente optio sapiente ut temporibus laborum. Ipsum expedita laborum reprehenderit praesentium. Nisi quae dolores neque."
    },
    "evidence": {
      "hasEvidence": "No"
    }
  },
  {
    "id": "427601",
    "referralDate": "2022-07-05T05:57:12.789Z",
    "referrer": {
      "name": "Brigitte Halvorson",
      "jobTitle": "Headteacher",
      "phoneNumber": "07979 765 333",
      "organisation": {
        "name": "Terry Group School",
        "address": {
          "line1": "1 The Avenue",
          "town": "London",
          "postcode": "W9 1ST"
        }
      }
    },
    "teacher": {
      "firstName": "Angus",
      "lastName": "Lehner",
      "hasAnotherName": "I do not know",
      "dateOfBirth": "2022-09-28T21:28:37.948Z",
      "hasNationalInsuranceNumber": "No",
      "hasTeacherReferenceNumber": "Yes",
      "trn": "4567814",
      "hasQTS": "No",
      "hasEmailAddress": "No",
      "hasPhoneNumber": "No",
      "address": {
        "line1": "1 The Walk",
        "town": "Manchester",
        "postcode": "M1 1AG"
      },
      "hasJobStartDate": "Yes",
      "jobStartDate": "2022-11-03T07:04:04.850Z",
      "areTheyStillEmployed": "Yes",
      "jobTitle": "Teaching assistant",
      "doesWorkAtSameOrganisation": "Yes",
      "roleDescriptionMethod": "I’ll describe their main duties",
      "isTeachingSomewhereElse": "No, they’re not teaching somewhere else"
    },
    "allegation": {
      "method": "I’ll do this later",
      "hasToldDBS": "No"
    },
    "previousAllegations": {
      "hasPreviousAllegations": "I do not know"
    },
    "evidence": {
      "hasEvidence": "Yes",
      "files": [
        {
          "name": "main-investigation.pdf",
          "size": "1MB",
          "category": "Documents of internal investigations and outcomes"
        },
        {
          "name": "police-investigation.pdf",
          "size": "3MB",
          "category": "Police investigations and reports"
        },
        {
          "name": "signed-withness-statements.pdf",
          "size": "2MB",
          "category": "Signed witness statements"
        },
        {
          "name": "cctv-footage.mp4",
          "size": "2MB",
          "category": "File notes concerning conduct, behaviour and attitude"
        }
      ]
    }
  },
  {
    "id": "576961",
    "referralDate": "2022-01-30T20:17:13.202Z",
    "referrer": {
      "name": "Justus MacGyver",
      "jobTitle": "Teacher",
      "phoneNumber": "07983 328 474",
      "organisation": {
        "name": "Brown - Johnston School",
        "address": {
          "line1": "1 The Avenue",
          "town": "London",
          "postcode": "W9 1ST"
        }
      }
    },
    "teacher": {
      "firstName": "Braden",
      "lastName": "Mertz",
      "hasAnotherName": "No",
      "dateOfBirth": "2021-12-13T08:14:51.813Z",
      "hasNationalInsuranceNumber": "No",
      "hasTeacherReferenceNumber": "No",
      "hasQTS": "I do not know",
      "hasEmailAddress": "No",
      "hasPhoneNumber": "No",
      "address": {
        "line1": "1 The Walk",
        "town": "Manchester",
        "postcode": "M1 1AG"
      },
      "hasJobStartDate": "Yes",
      "jobStartDate": "2022-07-04T23:25:48.805Z",
      "areTheyStillEmployed": "Yes",
      "jobTitle": "Headteacher",
      "doesWorkAtSameOrganisation": "No",
      "organisation": {
        "name": "Kilback, Lynch and Gerhold School",
        "address": {
          "line1": "1 The Avenue",
          "town": "London",
          "postcode": "W9 1ST"
        }
      },
      "roleDescriptionMethod": "I’ll describe their main duties",
      "isTeachingSomewhereElse": "Yes, they’re teaching somewhere else",
      "newOrganisation": {
        "name": "Huels and Sons School",
        "address": {
          "line1": "1 The Avenue",
          "town": "Manchester",
          "postcode": "M1 2PK"
        }
      }
    },
    "allegation": {
      "method": "I’ll do this later",
      "hasToldDBS": "No"
    },
    "previousAllegations": {
      "hasPreviousAllegations": "Yes",
      "method": "I’ll give details of the previous misconduct",
      "description": "Dicta quaerat porro possimus et. Recusandae omnis perspiciatis fuga molestiae dolorum nihil nesciunt. Ab debitis nesciunt rerum dolorem. Accusantium alias natus.\n\nHic quod perspiciatis reprehenderit natus ea recusandae enim neque. Ex animi rerum incidunt. Aliquam qui sit provident alias repellendus. Vitae corrupti architecto. A quibusdam inventore explicabo.\n\nVero nesciunt sapiente quae deserunt quod culpa illum exercitationem minima. Explicabo nemo non delectus cum quaerat ullam occaecati. Necessitatibus blanditiis ipsam dolorem accusamus ipsam iusto atque."
    },
    "evidence": {
      "hasEvidence": "No"
    }
  },
  {
    "id": "133565",
    "referralDate": "2022-05-05T08:24:35.893Z",
    "referrer": {
      "name": "Johathan Feest",
      "jobTitle": "Headteacher",
      "phoneNumber": "07972 756 090",
      "organisation": {
        "name": "Wolff Group School",
        "address": {
          "line1": "1 The Avenue",
          "town": "London",
          "postcode": "W9 1ST"
        }
      }
    },
    "teacher": {
      "firstName": "Wilmer",
      "lastName": "Gleason",
      "hasAnotherName": "No",
      "dateOfBirth": "2022-07-29T11:52:19.543Z",
      "hasNationalInsuranceNumber": "Yes",
      "nationalInsuranceNumber": "QQ 12 34 56 C",
      "hasTeacherReferenceNumber": "Yes",
      "trn": "4567814",
      "hasQTS": "No",
      "hasEmailAddress": "Yes",
      "emailAddress": "wilmer.gleason@gmail.com",
      "hasPhoneNumber": "No",
      "address": {
        "line1": "1 The Walk",
        "town": "Manchester",
        "postcode": "M1 1AG"
      },
      "hasJobStartDate": "Yes",
      "jobStartDate": "2022-06-30T22:36:03.511Z",
      "areTheyStillEmployed": "No, they’ve left the organisation",
      "jobEndDate": "2021-12-07T16:51:11.394Z",
      "jobEndReason": "I do not know",
      "jobTitle": "Teacher",
      "doesWorkAtSameOrganisation": "Yes",
      "roleDescriptionMethod": "I’ll upload a job description",
      "roleDescriptionFile": {
        "name": "job-description.pdf",
        "size": "1MB"
      },
      "isTeachingSomewhereElse": "No, they’re not teaching somewhere else"
    },
    "allegation": {
      "method": "I’ll do this later",
      "hasToldDBS": "Yes, I’ve told DBS"
    },
    "previousAllegations": {
      "hasPreviousAllegations": "No"
    },
    "evidence": {
      "hasEvidence": "No"
    }
  },
  {
    "id": "603250",
    "referralDate": "2022-09-22T02:24:41.070Z",
    "referrer": {
      "name": "Eleanore Bayer",
      "jobTitle": "Headteacher",
      "phoneNumber": "07927 611 099",
      "organisation": {
        "name": "Hartmann - Trantow School",
        "address": {
          "line1": "1 The Avenue",
          "town": "London",
          "postcode": "W9 1ST"
        }
      }
    },
    "teacher": {
      "firstName": "Friedrich",
      "lastName": "Harris",
      "hasAnotherName": "No",
      "dateOfBirth": "2022-04-29T22:31:18.229Z",
      "hasNationalInsuranceNumber": "Yes",
      "nationalInsuranceNumber": "QQ 12 34 56 C",
      "hasTeacherReferenceNumber": "No",
      "hasQTS": "I do not know",
      "hasEmailAddress": "No",
      "hasPhoneNumber": "No",
      "address": {
        "line1": "1 The Walk",
        "town": "Manchester",
        "postcode": "M1 1AG"
      },
      "hasJobStartDate": "Yes",
      "jobStartDate": "2022-04-29T20:47:39.378Z",
      "areTheyStillEmployed": "Yes",
      "jobTitle": "Teaching assistant",
      "doesWorkAtSameOrganisation": "No",
      "organisation": {
        "name": "Kerluke Inc School",
        "address": {
          "line1": "1 The Avenue",
          "town": "London",
          "postcode": "W9 1ST"
        }
      },
      "roleDescriptionMethod": "I’ll describe their main duties",
      "isTeachingSomewhereElse": "I do not know"
    },
    "allegation": {
      "method": "I’ll do this later",
      "hasToldDBS": "Yes, I’ve told DBS"
    },
    "previousAllegations": {
      "hasPreviousAllegations": "No"
    },
    "evidence": {
      "hasEvidence": "No"
    }
  },
  {
    "id": "854107",
    "referralDate": "2022-05-25T08:04:04.649Z",
    "referrer": {
      "name": "Efren Gottlieb",
      "jobTitle": "Teacher",
      "phoneNumber": "07911 132 696",
      "organisation": {
        "name": "Conn, Bradtke and Schamberger School",
        "address": {
          "line1": "1 The Avenue",
          "town": "London",
          "postcode": "W9 1ST"
        }
      }
    },
    "teacher": {
      "firstName": "Scotty",
      "lastName": "Hilpert",
      "hasAnotherName": "Yes",
      "otherName": "Bobsky",
      "dateOfBirth": "2022-11-12T15:20:06.179Z",
      "hasNationalInsuranceNumber": "Yes",
      "nationalInsuranceNumber": "QQ 12 34 56 C",
      "hasTeacherReferenceNumber": "Yes",
      "trn": "4567814",
      "hasQTS": "I do not know",
      "hasEmailAddress": "No",
      "hasPhoneNumber": "Yes",
      "phoneNumber": "07903 503 142",
      "address": {
        "line1": "1 The Walk",
        "town": "Manchester",
        "postcode": "M1 1AG"
      },
      "hasJobStartDate": "Yes",
      "jobStartDate": "2022-08-08T08:56:46.773Z",
      "areTheyStillEmployed": "They’re still employed but they’ve been suspended",
      "jobTitle": "Teaching assistant",
      "doesWorkAtSameOrganisation": "No",
      "organisation": {
        "name": "Zulauf Group School",
        "address": {
          "line1": "1 The Avenue",
          "town": "London",
          "postcode": "W9 1ST"
        }
      },
      "roleDescriptionMethod": "I’ll do this later",
      "isTeachingSomewhereElse": "I do not know"
    },
    "allegation": {
      "method": "I’ll upload the allegation details",
      "file": {
        "name": "allegation-details.pdf",
        "size": "2MB"
      },
      "hasToldDBS": "No"
    },
    "previousAllegations": {
      "hasPreviousAllegations": "I do not know"
    },
    "evidence": {
      "hasEvidence": "Yes",
      "files": [
        {
          "name": "main-investigation.pdf",
          "size": "1MB",
          "category": "Documents of internal investigations and outcomes"
        },
        {
          "name": "police-investigation.pdf",
          "size": "3MB",
          "category": "Police investigations and reports"
        },
        {
          "name": "signed-withness-statements.pdf",
          "size": "2MB",
          "category": "Signed witness statements"
        },
        {
          "name": "cctv-footage.mp4",
          "size": "2MB",
          "category": "File notes concerning conduct, behaviour and attitude"
        }
      ]
    }
  },
  {
    "id": "190566",
    "referralDate": "2022-02-02T22:41:00.341Z",
    "referrer": {
      "name": "Olen Cole",
      "jobTitle": "Teacher",
      "phoneNumber": "07955 460 704",
      "organisation": {
        "name": "Turcotte Inc School",
        "address": {
          "line1": "1 The Avenue",
          "town": "London",
          "postcode": "W9 1ST"
        }
      }
    },
    "teacher": {
      "firstName": "Johnson",
      "lastName": "Kozey",
      "hasAnotherName": "Yes",
      "otherName": "Bobsky",
      "dateOfBirth": "2022-01-10T21:22:04.776Z",
      "hasNationalInsuranceNumber": "No",
      "hasTeacherReferenceNumber": "Yes",
      "trn": "4567814",
      "hasQTS": "I do not know",
      "hasEmailAddress": "Yes",
      "emailAddress": "johnson.kozey@gmail.com",
      "hasPhoneNumber": "No",
      "address": {
        "line1": "1 The Walk",
        "town": "Manchester",
        "postcode": "M1 1AG"
      },
      "hasJobStartDate": "No",
      "areTheyStillEmployed": "They’re still employed but they’ve been suspended",
      "jobTitle": "Headteacher",
      "doesWorkAtSameOrganisation": "No",
      "organisation": {
        "name": "Kerluke Inc School",
        "address": {
          "line1": "1 The Avenue",
          "town": "London",
          "postcode": "W9 1ST"
        }
      },
      "roleDescriptionMethod": "I’ll do this later",
      "isTeachingSomewhereElse": "No, they’re not teaching somewhere else"
    },
    "allegation": {
      "method": "I’ll do this later",
      "hasToldDBS": "Yes, I’ve told DBS"
    },
    "previousAllegations": {
      "hasPreviousAllegations": "Yes",
      "method": "I’ll give details of the previous misconduct",
      "description": "Doloribus nam consectetur repudiandae minima nisi amet unde magni. Recusandae sed facilis suscipit deserunt maiores quis facere voluptas atque. Laborum vel velit dolores omnis unde accusantium sunt maiores animi.\n\nQuaerat ex quam soluta blanditiis labore voluptate impedit aut. Debitis rerum deleniti aliquam veniam. Molestiae at molestias quod odio. Eum sunt vel illo consequuntur delectus iure dignissimos. Alias debitis et. Exercitationem ratione dolorem.\n\nIncidunt laudantium harum. Ea nisi enim magni quaerat quidem repellendus fuga. Laboriosam enim facilis."
    },
    "evidence": {
      "hasEvidence": "No"
    }
  },
  {
    "id": "125299",
    "referralDate": "2022-11-08T17:11:26.467Z",
    "referrer": {
      "name": "Marcelina Daugherty",
      "jobTitle": "Teaching assistant",
      "phoneNumber": "07929 267 470",
      "organisation": {
        "name": "Koss and Sons School",
        "address": {
          "line1": "1 The Avenue",
          "town": "London",
          "postcode": "W9 1ST"
        }
      }
    },
    "teacher": {
      "firstName": "Berta",
      "lastName": "Hilll",
      "hasAnotherName": "No",
      "dateOfBirth": "2022-02-04T16:53:20.106Z",
      "hasNationalInsuranceNumber": "Yes",
      "nationalInsuranceNumber": "QQ 12 34 56 C",
      "hasTeacherReferenceNumber": "Yes",
      "trn": "4567814",
      "hasQTS": "Yes",
      "hasEmailAddress": "Yes",
      "emailAddress": "berta.hilll@gmail.com",
      "hasPhoneNumber": "Yes",
      "phoneNumber": "07965 345 112",
      "address": {
        "line1": "1 The Walk",
        "town": "Manchester",
        "postcode": "M1 1AG"
      },
      "hasJobStartDate": "Yes",
      "jobStartDate": "2022-06-30T17:57:33.417Z",
      "areTheyStillEmployed": "No, they’ve left the organisation",
      "jobEndDate": "2022-04-02T14:09:16.001Z",
      "jobEndReason": "Retired",
      "jobTitle": "Teaching assistant",
      "doesWorkAtSameOrganisation": "Yes",
      "roleDescriptionMethod": "I’ll do this later",
      "isTeachingSomewhereElse": "No, they’re not teaching somewhere else"
    },
    "allegation": {
      "method": "I’ll do this later",
      "hasToldDBS": "No"
    },
    "previousAllegations": {
      "hasPreviousAllegations": "Yes",
      "method": "I’ll give details of the previous misconduct",
      "description": "Qui alias excepturi sapiente eligendi tempora sed. Officiis ad voluptate cumque. Laboriosam adipisci iusto quas explicabo numquam molestias libero molestias illum. Voluptatem totam quas veniam facilis repellendus.\n\nAd inventore distinctio. Excepturi ipsum cum delectus. Nostrum eum adipisci suscipit distinctio neque modi nam eaque cum. Provident omnis necessitatibus animi quis.\n\nCommodi est illo voluptatibus eius a ea nostrum recusandae. In sunt officia voluptates itaque suscipit vero commodi delectus recusandae. Cumque eum quas corrupti vitae nam eius id hic. Nesciunt commodi at tenetur numquam dignissimos quas dolore. Voluptatibus omnis maiores ab praesentium quibusdam ea rem cupiditate."
    },
    "evidence": {
      "hasEvidence": "Yes",
      "files": [
        {
          "name": "main-investigation.pdf",
          "size": "1MB",
          "category": "Documents of internal investigations and outcomes"
        },
        {
          "name": "police-investigation.pdf",
          "size": "3MB",
          "category": "Police investigations and reports"
        },
        {
          "name": "signed-withness-statements.pdf",
          "size": "2MB",
          "category": "Signed witness statements"
        },
        {
          "name": "cctv-footage.mp4",
          "size": "2MB",
          "category": "File notes concerning conduct, behaviour and attitude"
        }
      ]
    }
  },
  {
    "id": "831078",
    "referralDate": "2022-02-23T16:43:23.170Z",
    "referrer": {
      "name": "Brody Pouros",
      "jobTitle": "Teaching assistant",
      "phoneNumber": "07913 293 086",
      "organisation": {
        "name": "Mann, Ankunding and Wyman School",
        "address": {
          "line1": "1 The Avenue",
          "town": "London",
          "postcode": "W9 1ST"
        }
      }
    },
    "teacher": {
      "firstName": "Lela",
      "lastName": "Skiles",
      "hasAnotherName": "No",
      "dateOfBirth": "2022-03-31T12:42:40.974Z",
      "hasNationalInsuranceNumber": "Yes",
      "nationalInsuranceNumber": "QQ 12 34 56 C",
      "hasTeacherReferenceNumber": "No",
      "hasQTS": "I do not know",
      "hasEmailAddress": "No",
      "hasPhoneNumber": "No",
      "address": {
        "line1": "1 The Walk",
        "town": "Manchester",
        "postcode": "M1 1AG"
      },
      "hasJobStartDate": "No",
      "areTheyStillEmployed": "No, they’ve left the organisation",
      "jobEndDate": "2022-07-12T22:12:24.552Z",
      "jobEndReason": "Dismissed",
      "jobTitle": "Teaching assistant",
      "doesWorkAtSameOrganisation": "No",
      "organisation": {
        "name": "Lebsack Inc School",
        "address": {
          "line1": "1 The Avenue",
          "town": "London",
          "postcode": "W9 1ST"
        }
      },
      "roleDescriptionMethod": "I’ll upload a job description",
      "roleDescriptionFile": {
        "name": "job-description.pdf",
        "size": "1MB"
      },
      "isTeachingSomewhereElse": "I do not know"
    },
    "allegation": {
      "method": "I’ll do this later",
      "hasToldDBS": "No"
    },
    "previousAllegations": {
      "hasPreviousAllegations": "No"
    },
    "evidence": {
      "hasEvidence": "Yes",
      "files": [
        {
          "name": "main-investigation.pdf",
          "size": "1MB",
          "category": "Documents of internal investigations and outcomes"
        },
        {
          "name": "police-investigation.pdf",
          "size": "3MB",
          "category": "Police investigations and reports"
        },
        {
          "name": "signed-withness-statements.pdf",
          "size": "2MB",
          "category": "Signed witness statements"
        },
        {
          "name": "cctv-footage.mp4",
          "size": "2MB",
          "category": "File notes concerning conduct, behaviour and attitude"
        }
      ]
    }
  },
  {
    "id": "641123",
    "referralDate": "2022-01-20T11:06:23.926Z",
    "referrer": {
      "name": "Elvis Dickens",
      "jobTitle": "Teacher",
      "phoneNumber": "07980 140 945",
      "organisation": {
        "name": "Dooley LLC School",
        "address": {
          "line1": "1 The Avenue",
          "town": "London",
          "postcode": "W9 1ST"
        }
      }
    },
    "teacher": {
      "firstName": "Lemuel",
      "lastName": "Wisoky",
      "hasAnotherName": "Yes",
      "otherName": "Bobsky",
      "dateOfBirth": "2022-06-15T12:12:01.258Z",
      "hasNationalInsuranceNumber": "No",
      "hasTeacherReferenceNumber": "Yes",
      "trn": "4567814",
      "hasQTS": "No",
      "hasEmailAddress": "Yes",
      "emailAddress": "lemuel.wisoky@gmail.com",
      "hasPhoneNumber": "No",
      "address": {
        "line1": "1 The Walk",
        "town": "Manchester",
        "postcode": "M1 1AG"
      },
      "hasJobStartDate": "No",
      "areTheyStillEmployed": "No, they’ve left the organisation",
      "jobEndDate": "2022-07-14T11:22:25.759Z",
      "jobEndReason": "I do not know",
      "jobTitle": "Teacher",
      "doesWorkAtSameOrganisation": "No",
      "organisation": {
        "name": "Labadie Inc School",
        "address": {
          "line1": "1 The Avenue",
          "town": "London",
          "postcode": "W9 1ST"
        }
      },
      "roleDescriptionMethod": "I’ll upload a job description",
      "roleDescriptionFile": {
        "name": "job-description.pdf",
        "size": "1MB"
      },
      "isTeachingSomewhereElse": "I do not know"
    },
    "allegation": {
      "method": "I’ll do this later",
      "hasToldDBS": "Yes, I’ve told DBS"
    },
    "previousAllegations": {
      "hasPreviousAllegations": "Yes",
      "method": "I’ll give details of the previous misconduct",
      "description": "Eius fugiat molestiae sed fugiat voluptas. Excepturi porro quasi vero sint voluptate suscipit amet ratione. Explicabo dolore omnis dolorem dolore debitis deserunt quo. Voluptate esse nisi et eos. Porro impedit sint amet.\n\nMinima quasi ea architecto sunt. Velit blanditiis alias recusandae odio. Officiis recusandae eligendi deserunt debitis error. Soluta neque quis inventore optio eligendi nesciunt.\n\nAtque dolor veniam eius maiores aliquid a sed. Labore quas ad ea assumenda quo rem consequatur. Fuga numquam minima vitae blanditiis non error suscipit. Praesentium perferendis quae id."
    },
    "evidence": {
      "hasEvidence": "No"
    }
  },
  {
    "id": "148557",
    "referralDate": "2022-11-04T12:51:07.397Z",
    "referrer": {
      "name": "Nolan Boehm",
      "jobTitle": "Headteacher",
      "phoneNumber": "07942 787 753",
      "organisation": {
        "name": "Friesen - Wilkinson School",
        "address": {
          "line1": "1 The Avenue",
          "town": "London",
          "postcode": "W9 1ST"
        }
      }
    },
    "teacher": {
      "firstName": "Jeremy",
      "lastName": "Roberts",
      "hasAnotherName": "I do not know",
      "dateOfBirth": "2022-07-28T18:43:22.294Z",
      "hasNationalInsuranceNumber": "No",
      "hasTeacherReferenceNumber": "No",
      "hasQTS": "I do not know",
      "hasEmailAddress": "No",
      "hasPhoneNumber": "No",
      "address": {
        "line1": "1 The Walk",
        "town": "Manchester",
        "postcode": "M1 1AG"
      },
      "hasJobStartDate": "Yes",
      "jobStartDate": "2021-12-23T16:54:28.940Z",
      "areTheyStillEmployed": "No, they’ve left the organisation",
      "jobEndDate": "2022-11-29T21:39:59.091Z",
      "jobEndReason": "Dismissed",
      "jobTitle": "Teacher",
      "doesWorkAtSameOrganisation": "No",
      "organisation": {
        "name": "Kihn LLC School",
        "address": {
          "line1": "1 The Avenue",
          "town": "London",
          "postcode": "W9 1ST"
        }
      },
      "roleDescriptionMethod": "I’ll describe their main duties",
      "isTeachingSomewhereElse": "No, they’re not teaching somewhere else"
    },
    "allegation": {
      "method": "I’ll upload the allegation details",
      "file": {
        "name": "allegation-details.pdf",
        "size": "2MB"
      },
      "hasToldDBS": "Yes, I’ve told DBS"
    },
    "previousAllegations": {
      "hasPreviousAllegations": "Yes",
      "method": "I’ll do this later"
    },
    "evidence": {
      "hasEvidence": "Yes",
      "files": [
        {
          "name": "main-investigation.pdf",
          "size": "1MB",
          "category": "Documents of internal investigations and outcomes"
        },
        {
          "name": "police-investigation.pdf",
          "size": "3MB",
          "category": "Police investigations and reports"
        },
        {
          "name": "signed-withness-statements.pdf",
          "size": "2MB",
          "category": "Signed witness statements"
        },
        {
          "name": "cctv-footage.mp4",
          "size": "2MB",
          "category": "File notes concerning conduct, behaviour and attitude"
        }
      ]
    }
  },
  {
    "id": "395308",
    "referralDate": "2021-12-15T00:08:09.565Z",
    "referrer": {
      "name": "Dewayne Zboncak",
      "jobTitle": "Teacher",
      "phoneNumber": "07920 341 401",
      "organisation": {
        "name": "Bradtke and Sons School",
        "address": {
          "line1": "1 The Avenue",
          "town": "London",
          "postcode": "W9 1ST"
        }
      }
    },
    "teacher": {
      "firstName": "Rachael",
      "lastName": "Collier",
      "hasAnotherName": "I do not know",
      "dateOfBirth": "2022-08-11T21:48:12.404Z",
      "hasNationalInsuranceNumber": "Yes",
      "nationalInsuranceNumber": "QQ 12 34 56 C",
      "hasTeacherReferenceNumber": "Yes",
      "trn": "4567814",
      "hasQTS": "I do not know",
      "hasEmailAddress": "No",
      "hasPhoneNumber": "No",
      "address": {
        "line1": "1 The Walk",
        "town": "Manchester",
        "postcode": "M1 1AG"
      },
      "hasJobStartDate": "No",
      "areTheyStillEmployed": "They’re still employed but they’ve been suspended",
      "jobTitle": "Teacher",
      "doesWorkAtSameOrganisation": "No",
      "organisation": {
        "name": "Metz, Pfannerstill and Ankunding School",
        "address": {
          "line1": "1 The Avenue",
          "town": "London",
          "postcode": "W9 1ST"
        }
      },
      "roleDescriptionMethod": "I’ll upload a job description",
      "roleDescriptionFile": {
        "name": "job-description.pdf",
        "size": "1MB"
      },
      "isTeachingSomewhereElse": "Yes, they’re teaching somewhere else",
      "newOrganisation": {
        "name": "Bradtke Group School",
        "address": {
          "line1": "1 The Avenue",
          "town": "Manchester",
          "postcode": "M1 2PK"
        }
      }
    },
    "allegation": {
      "method": "I’ll give details of the allegation",
      "description": "Tempore at ducimus provident quod aspernatur. Assumenda facilis at ullam quo. Eius in cumque eius commodi consequuntur minus. Modi numquam ad. Earum rem reprehenderit.\n\nQuo optio sequi sunt numquam ipsam. Nemo veritatis adipisci veniam. Impedit sunt quam tempore tenetur dolorum. Placeat eum temporibus asperiores consectetur aperiam porro quam. Sequi corrupti explicabo eius.\n\nNam enim voluptatem est occaecati id. Veritatis officia ipsam. Delectus excepturi facilis facere doloribus praesentium rem nisi hic harum. Accusamus voluptas consequatur. Aperiam veritatis tempora.",
      "hasToldDBS": "Yes, I’ve told DBS"
    },
    "previousAllegations": {
      "hasPreviousAllegations": "Yes",
      "method": "I’ll give details of the previous misconduct",
      "description": "Corrupti autem nobis inventore sed odit nesciunt fuga nisi officia. Quas necessitatibus aperiam est dignissimos. Deserunt natus corrupti voluptates alias distinctio nam exercitationem impedit.\n\nA ullam soluta repudiandae doloremque. Nobis iusto ipsum. Hic debitis eaque assumenda expedita voluptatem repellendus aspernatur consectetur at.\n\nUnde similique minima voluptatibus hic. Quam voluptate repellat molestias a qui eaque ad consequatur aut. Dolor numquam quas nihil numquam. Quo magnam omnis. Labore nihil non deleniti inventore blanditiis eaque illo."
    },
    "evidence": {
      "hasEvidence": "Yes",
      "files": [
        {
          "name": "main-investigation.pdf",
          "size": "1MB",
          "category": "Documents of internal investigations and outcomes"
        },
        {
          "name": "police-investigation.pdf",
          "size": "3MB",
          "category": "Police investigations and reports"
        },
        {
          "name": "signed-withness-statements.pdf",
          "size": "2MB",
          "category": "Signed witness statements"
        },
        {
          "name": "cctv-footage.mp4",
          "size": "2MB",
          "category": "File notes concerning conduct, behaviour and attitude"
        }
      ]
    }
  },
  {
    "id": "530617",
    "referralDate": "2022-04-01T04:17:31.095Z",
    "referrer": {
      "name": "Maryam Mante",
      "jobTitle": "Teacher",
      "phoneNumber": "07955 627 796",
      "organisation": {
        "name": "Kassulke - Hintz School",
        "address": {
          "line1": "1 The Avenue",
          "town": "London",
          "postcode": "W9 1ST"
        }
      }
    },
    "teacher": {
      "firstName": "Juliana",
      "lastName": "Schowalter",
      "hasAnotherName": "Yes",
      "otherName": "Bobsky",
      "dateOfBirth": "2022-02-12T10:07:57.359Z",
      "hasNationalInsuranceNumber": "Yes",
      "nationalInsuranceNumber": "QQ 12 34 56 C",
      "hasTeacherReferenceNumber": "Yes",
      "trn": "4567814",
      "hasQTS": "No",
      "hasEmailAddress": "No",
      "hasPhoneNumber": "Yes",
      "phoneNumber": "07966 116 920",
      "address": {
        "line1": "1 The Walk",
        "town": "Manchester",
        "postcode": "M1 1AG"
      },
      "hasJobStartDate": "Yes",
      "jobStartDate": "2022-02-03T10:38:04.892Z",
      "areTheyStillEmployed": "They’re still employed but they’ve been suspended",
      "jobTitle": "Teacher",
      "doesWorkAtSameOrganisation": "Yes",
      "roleDescriptionMethod": "I’ll upload a job description",
      "roleDescriptionFile": {
        "name": "job-description.pdf",
        "size": "1MB"
      },
      "isTeachingSomewhereElse": "Yes, they’re teaching somewhere else",
      "newOrganisation": {
        "name": "Cummings, Gerlach and Jerde School",
        "address": {
          "line1": "1 The Avenue",
          "town": "Manchester",
          "postcode": "M1 2PK"
        }
      }
    },
    "allegation": {
      "method": "I’ll do this later",
      "hasToldDBS": "No"
    },
    "previousAllegations": {
      "hasPreviousAllegations": "I do not know"
    },
    "evidence": {
      "hasEvidence": "No"
    }
  },
  {
    "id": "841292",
    "referralDate": "2022-02-23T00:19:17.441Z",
    "referrer": {
      "name": "Norma Roberts",
      "jobTitle": "Teacher",
      "phoneNumber": "07916 522 319",
      "organisation": {
        "name": "Bernier and Sons School",
        "address": {
          "line1": "1 The Avenue",
          "town": "London",
          "postcode": "W9 1ST"
        }
      }
    },
    "teacher": {
      "firstName": "Stephen",
      "lastName": "Bosco",
      "hasAnotherName": "I do not know",
      "dateOfBirth": "2022-11-01T07:50:40.028Z",
      "hasNationalInsuranceNumber": "No",
      "hasTeacherReferenceNumber": "No",
      "hasQTS": "I do not know",
      "hasEmailAddress": "Yes",
      "emailAddress": "stephen.bosco@gmail.com",
      "hasPhoneNumber": "Yes",
      "phoneNumber": "07961 908 050",
      "address": {
        "line1": "1 The Walk",
        "town": "Manchester",
        "postcode": "M1 1AG"
      },
      "hasJobStartDate": "Yes",
      "jobStartDate": "2022-07-26T01:03:50.105Z",
      "areTheyStillEmployed": "They’re still employed but they’ve been suspended",
      "jobTitle": "Teacher",
      "doesWorkAtSameOrganisation": "Yes",
      "roleDescriptionMethod": "I’ll do this later",
      "isTeachingSomewhereElse": "I do not know"
    },
    "allegation": {
      "method": "I’ll do this later",
      "hasToldDBS": "Yes, I’ve told DBS"
    },
    "previousAllegations": {
      "hasPreviousAllegations": "Yes",
      "method": "I’ll upload the previous misconduct details",
      "file": {
        "name": "previous-misconduct-details.pdf",
        "size": "2MB"
      }
    },
    "evidence": {
      "hasEvidence": "Yes",
      "files": [
        {
          "name": "main-investigation.pdf",
          "size": "1MB",
          "category": "Documents of internal investigations and outcomes"
        },
        {
          "name": "police-investigation.pdf",
          "size": "3MB",
          "category": "Police investigations and reports"
        },
        {
          "name": "signed-withness-statements.pdf",
          "size": "2MB",
          "category": "Signed witness statements"
        },
        {
          "name": "cctv-footage.mp4",
          "size": "2MB",
          "category": "File notes concerning conduct, behaviour and attitude"
        }
      ]
    }
  },
  {
    "id": "962204",
    "referralDate": "2022-07-24T12:16:21.953Z",
    "referrer": {
      "name": "Keegan Kulas",
      "jobTitle": "Teaching assistant",
      "phoneNumber": "07907 731 630",
      "organisation": {
        "name": "Cummerata Group School",
        "address": {
          "line1": "1 The Avenue",
          "town": "London",
          "postcode": "W9 1ST"
        }
      }
    },
    "teacher": {
      "firstName": "Laura",
      "lastName": "Cole",
      "hasAnotherName": "I do not know",
      "dateOfBirth": "2022-09-17T08:11:19.654Z",
      "hasNationalInsuranceNumber": "Yes",
      "nationalInsuranceNumber": "QQ 12 34 56 C",
      "hasTeacherReferenceNumber": "No",
      "hasQTS": "I do not know",
      "hasEmailAddress": "No",
      "hasPhoneNumber": "Yes",
      "phoneNumber": "07994 941 147",
      "address": {
        "line1": "1 The Walk",
        "town": "Manchester",
        "postcode": "M1 1AG"
      },
      "hasJobStartDate": "Yes",
      "jobStartDate": "2022-11-21T06:40:32.710Z",
      "areTheyStillEmployed": "No, they’ve left the organisation",
      "jobEndDate": "2022-02-20T12:10:50.836Z",
      "jobEndReason": "Dismissed",
      "jobTitle": "Teacher",
      "doesWorkAtSameOrganisation": "Yes",
      "roleDescriptionMethod": "I’ll do this later",
      "isTeachingSomewhereElse": "No, they’re not teaching somewhere else"
    },
    "allegation": {
      "method": "I’ll do this later",
      "hasToldDBS": "Yes, I’ve told DBS"
    },
    "previousAllegations": {
      "hasPreviousAllegations": "No"
    },
    "evidence": {
      "hasEvidence": "Yes",
      "files": [
        {
          "name": "main-investigation.pdf",
          "size": "1MB",
          "category": "Documents of internal investigations and outcomes"
        },
        {
          "name": "police-investigation.pdf",
          "size": "3MB",
          "category": "Police investigations and reports"
        },
        {
          "name": "signed-withness-statements.pdf",
          "size": "2MB",
          "category": "Signed witness statements"
        },
        {
          "name": "cctv-footage.mp4",
          "size": "2MB",
          "category": "File notes concerning conduct, behaviour and attitude"
        }
      ]
    }
  },
  {
    "id": "421964",
    "referralDate": "2022-03-03T04:06:13.670Z",
    "referrer": {
      "name": "Reilly Gerlach",
      "jobTitle": "Teaching assistant",
      "phoneNumber": "07948 540 623",
      "organisation": {
        "name": "Aufderhar Inc School",
        "address": {
          "line1": "1 The Avenue",
          "town": "London",
          "postcode": "W9 1ST"
        }
      }
    },
    "teacher": {
      "firstName": "Lynn",
      "lastName": "Lowe",
      "hasAnotherName": "No",
      "dateOfBirth": "2022-02-07T17:35:47.419Z",
      "hasNationalInsuranceNumber": "No",
      "hasTeacherReferenceNumber": "Yes",
      "trn": "4567814",
      "hasQTS": "I do not know",
      "hasEmailAddress": "No",
      "hasPhoneNumber": "No",
      "address": {
        "line1": "1 The Walk",
        "town": "Manchester",
        "postcode": "M1 1AG"
      },
      "hasJobStartDate": "Yes",
      "jobStartDate": "2022-08-19T23:49:04.414Z",
      "areTheyStillEmployed": "No, they’ve left the organisation",
      "jobEndDate": "2022-07-06T09:21:21.965Z",
      "jobEndReason": "I do not know",
      "jobTitle": "Teaching assistant",
      "doesWorkAtSameOrganisation": "Yes",
      "roleDescriptionMethod": "I’ll do this later",
      "isTeachingSomewhereElse": "No, they’re not teaching somewhere else"
    },
    "allegation": {
      "method": "I’ll give details of the allegation",
      "description": "Non porro mollitia nihil architecto animi. Officiis ratione dignissimos modi ad eos facere voluptatibus. Delectus ullam totam. Veritatis nostrum sapiente impedit tempora impedit hic quia. Dolore amet officia atque.\n\nAtque soluta non tempore veritatis quis occaecati quidem. Vel ipsam facere ducimus numquam aliquam. Mollitia amet totam fugiat eum ullam. Laudantium iure enim eius animi temporibus dolore saepe. Recusandae explicabo qui eligendi non. Occaecati natus commodi.\n\nMolestiae sapiente qui similique praesentium perferendis vero. Debitis repellat dolor et esse laborum dignissimos officiis. Omnis consequuntur quisquam voluptate hic ipsam ab distinctio. Veniam ullam quam ipsa nisi veritatis.",
      "hasToldDBS": "No"
    },
    "previousAllegations": {
      "hasPreviousAllegations": "Yes",
      "method": "I’ll do this later"
    },
    "evidence": {
      "hasEvidence": "Yes",
      "files": [
        {
          "name": "main-investigation.pdf",
          "size": "1MB",
          "category": "Documents of internal investigations and outcomes"
        },
        {
          "name": "police-investigation.pdf",
          "size": "3MB",
          "category": "Police investigations and reports"
        },
        {
          "name": "signed-withness-statements.pdf",
          "size": "2MB",
          "category": "Signed witness statements"
        },
        {
          "name": "cctv-footage.mp4",
          "size": "2MB",
          "category": "File notes concerning conduct, behaviour and attitude"
        }
      ]
    }
  },
  {
    "id": "484570",
    "referralDate": "2022-04-19T23:41:47.866Z",
    "referrer": {
      "name": "Marianne Heidenreich",
      "jobTitle": "Teacher",
      "phoneNumber": "07937 027 891",
      "organisation": {
        "name": "Mills, Gulgowski and Zboncak School",
        "address": {
          "line1": "1 The Avenue",
          "town": "London",
          "postcode": "W9 1ST"
        }
      }
    },
    "teacher": {
      "firstName": "Piper",
      "lastName": "Walsh",
      "hasAnotherName": "Yes",
      "otherName": "Bobsky",
      "dateOfBirth": "2021-12-24T19:52:30.818Z",
      "hasNationalInsuranceNumber": "No",
      "hasTeacherReferenceNumber": "No",
      "hasQTS": "No",
      "hasEmailAddress": "No",
      "hasPhoneNumber": "No",
      "address": {
        "line1": "1 The Walk",
        "town": "Manchester",
        "postcode": "M1 1AG"
      },
      "hasJobStartDate": "No",
      "areTheyStillEmployed": "Yes",
      "jobTitle": "Teaching assistant",
      "doesWorkAtSameOrganisation": "Yes",
      "roleDescriptionMethod": "I’ll describe their main duties",
      "isTeachingSomewhereElse": "Yes, they’re teaching somewhere else",
      "newOrganisation": {
        "name": "Renner Group School",
        "address": {
          "line1": "1 The Avenue",
          "town": "Manchester",
          "postcode": "M1 2PK"
        }
      }
    },
    "allegation": {
      "method": "I’ll give details of the allegation",
      "description": "Explicabo culpa quibusdam eligendi. Ad eos earum. Corporis deserunt culpa ratione qui tempora voluptatum. Ipsa accusantium enim perspiciatis error.\n\nQuasi id quaerat aperiam magnam animi. Ullam facilis quo in debitis eaque similique architecto dicta ullam. Animi laborum nesciunt cumque officiis cum eius cupiditate.\n\nQuas modi quidem totam possimus in sit ut occaecati perferendis. Ipsam reprehenderit voluptatum doloremque explicabo distinctio. Nisi odio tempore. Architecto numquam veritatis.",
      "hasToldDBS": "No"
    },
    "previousAllegations": {
      "hasPreviousAllegations": "I do not know"
    },
    "evidence": {
      "hasEvidence": "No"
    }
  },
  {
    "id": "801131",
    "referralDate": "2022-05-23T14:58:43.618Z",
    "referrer": {
      "name": "Domenica Hills",
      "jobTitle": "Teaching assistant",
      "phoneNumber": "07945 068 135",
      "organisation": {
        "name": "Hodkiewicz - Bogan School",
        "address": {
          "line1": "1 The Avenue",
          "town": "London",
          "postcode": "W9 1ST"
        }
      }
    },
    "teacher": {
      "firstName": "Ismael",
      "lastName": "Hilll",
      "hasAnotherName": "Yes",
      "otherName": "Bobsky",
      "dateOfBirth": "2022-03-20T07:31:54.113Z",
      "hasNationalInsuranceNumber": "No",
      "hasTeacherReferenceNumber": "No",
      "hasQTS": "I do not know",
      "hasEmailAddress": "Yes",
      "emailAddress": "ismael.hilll@gmail.com",
      "hasPhoneNumber": "No",
      "address": {
        "line1": "1 The Walk",
        "town": "Manchester",
        "postcode": "M1 1AG"
      },
      "hasJobStartDate": "No",
      "areTheyStillEmployed": "No, they’ve left the organisation",
      "jobEndDate": "2022-03-27T08:08:20.507Z",
      "jobEndReason": "Retired",
      "jobTitle": "Teaching assistant",
      "doesWorkAtSameOrganisation": "Yes",
      "roleDescriptionMethod": "I’ll describe their main duties",
      "isTeachingSomewhereElse": "Yes, they’re teaching somewhere else",
      "newOrganisation": {
        "name": "Kautzer Group School",
        "address": {
          "line1": "1 The Avenue",
          "town": "Manchester",
          "postcode": "M1 2PK"
        }
      }
    },
    "allegation": {
      "method": "I’ll give details of the allegation",
      "description": "Ullam dolorum quod. Repellendus molestias eaque provident ullam odit vel. Nihil architecto sint debitis maxime. Exercitationem asperiores exercitationem rem autem consequatur dolorum magnam aut. Quam numquam voluptates. Reiciendis voluptas aliquam tempore voluptatum.\n\nDucimus eum velit iusto illum nesciunt eius. Laboriosam ut dolores ipsa inventore corporis dolores. Porro delectus dolore provident temporibus suscipit sed. Autem tenetur ipsum deserunt aliquam ut voluptas consequatur eum molestiae. Sed voluptate mollitia consequatur similique.\n\nNesciunt molestiae quibusdam numquam eveniet tenetur minima dolorum dolorem quas. Debitis dolor quas sapiente hic minima a iure. Praesentium debitis at sunt.",
      "hasToldDBS": "Yes, I’ve told DBS"
    },
    "previousAllegations": {
      "hasPreviousAllegations": "I do not know"
    },
    "evidence": {
      "hasEvidence": "No"
    }
  },
  {
    "id": "151843",
    "referralDate": "2022-07-18T21:38:12.992Z",
    "referrer": {
      "name": "Curtis Wisoky",
      "jobTitle": "Headteacher",
      "phoneNumber": "07999 749 099",
      "organisation": {
        "name": "Hegmann, Swaniawski and Cormier School",
        "address": {
          "line1": "1 The Avenue",
          "town": "London",
          "postcode": "W9 1ST"
        }
      }
    },
    "teacher": {
      "firstName": "Aubree",
      "lastName": "Grimes",
      "hasAnotherName": "I do not know",
      "dateOfBirth": "2022-03-05T22:53:34.916Z",
      "hasNationalInsuranceNumber": "Yes",
      "nationalInsuranceNumber": "QQ 12 34 56 C",
      "hasTeacherReferenceNumber": "Yes",
      "trn": "4567814",
      "hasQTS": "I do not know",
      "hasEmailAddress": "No",
      "hasPhoneNumber": "Yes",
      "phoneNumber": "07961 459 305",
      "address": {
        "line1": "1 The Walk",
        "town": "Manchester",
        "postcode": "M1 1AG"
      },
      "hasJobStartDate": "No",
      "areTheyStillEmployed": "No, they’ve left the organisation",
      "jobEndDate": "2022-11-11T00:31:30.722Z",
      "jobEndReason": "Retired",
      "jobTitle": "Teaching assistant",
      "doesWorkAtSameOrganisation": "Yes",
      "roleDescriptionMethod": "I’ll upload a job description",
      "roleDescriptionFile": {
        "name": "job-description.pdf",
        "size": "1MB"
      },
      "isTeachingSomewhereElse": "No, they’re not teaching somewhere else"
    },
    "allegation": {
      "method": "I’ll upload the allegation details",
      "file": {
        "name": "allegation-details.pdf",
        "size": "2MB"
      },
      "hasToldDBS": "Yes, I’ve told DBS"
    },
    "previousAllegations": {
      "hasPreviousAllegations": "Yes",
      "method": "I’ll do this later"
    },
    "evidence": {
      "hasEvidence": "No"
    }
  },
  {
    "id": "322191",
    "referralDate": "2022-07-23T19:37:09.772Z",
    "referrer": {
      "name": "King Graham",
      "jobTitle": "Headteacher",
      "phoneNumber": "07974 354 536",
      "organisation": {
        "name": "Hyatt, Funk and Langworth School",
        "address": {
          "line1": "1 The Avenue",
          "town": "London",
          "postcode": "W9 1ST"
        }
      }
    },
    "teacher": {
      "firstName": "Luz",
      "lastName": "Koch",
      "hasAnotherName": "Yes",
      "otherName": "Bobsky",
      "dateOfBirth": "2022-10-31T09:30:29.147Z",
      "hasNationalInsuranceNumber": "Yes",
      "nationalInsuranceNumber": "QQ 12 34 56 C",
      "hasTeacherReferenceNumber": "Yes",
      "trn": "4567814",
      "hasQTS": "I do not know",
      "hasEmailAddress": "Yes",
      "emailAddress": "luz.koch@gmail.com",
      "hasPhoneNumber": "Yes",
      "phoneNumber": "07902 233 284",
      "address": {
        "line1": "1 The Walk",
        "town": "Manchester",
        "postcode": "M1 1AG"
      },
      "hasJobStartDate": "Yes",
      "jobStartDate": "2022-06-20T21:07:44.468Z",
      "areTheyStillEmployed": "Yes",
      "jobTitle": "Headteacher",
      "doesWorkAtSameOrganisation": "No",
      "organisation": {
        "name": "Gleason - Mosciski School",
        "address": {
          "line1": "1 The Avenue",
          "town": "London",
          "postcode": "W9 1ST"
        }
      },
      "roleDescriptionMethod": "I’ll do this later",
      "isTeachingSomewhereElse": "I do not know"
    },
    "allegation": {
      "method": "I’ll upload the allegation details",
      "file": {
        "name": "allegation-details.pdf",
        "size": "2MB"
      },
      "hasToldDBS": "No"
    },
    "previousAllegations": {
      "hasPreviousAllegations": "Yes",
      "method": "I’ll give details of the previous misconduct",
      "description": "Explicabo occaecati natus dolorum ullam. Architecto dolores soluta. Consequatur dignissimos ullam vitae. Nulla quisquam quisquam exercitationem. Id laborum mollitia.\n\nMolestias neque laboriosam explicabo quos maxime. Dolore sequi rem praesentium consectetur odio dolor. Voluptatum labore possimus tenetur perspiciatis libero molestiae odit quis. Temporibus natus odit tempore. Mollitia eos illo fuga. Quae beatae veniam sit est totam ea.\n\nNisi possimus nulla dolor saepe in quo. Dolores excepturi vitae impedit tenetur. Perspiciatis explicabo dolorem perspiciatis perferendis ipsum sapiente quam."
    },
    "evidence": {
      "hasEvidence": "Yes",
      "files": [
        {
          "name": "main-investigation.pdf",
          "size": "1MB",
          "category": "Documents of internal investigations and outcomes"
        },
        {
          "name": "police-investigation.pdf",
          "size": "3MB",
          "category": "Police investigations and reports"
        },
        {
          "name": "signed-withness-statements.pdf",
          "size": "2MB",
          "category": "Signed witness statements"
        },
        {
          "name": "cctv-footage.mp4",
          "size": "2MB",
          "category": "File notes concerning conduct, behaviour and attitude"
        }
      ]
    }
  },
  {
    "id": "708244",
    "referralDate": "2022-01-20T08:05:51.762Z",
    "referrer": {
      "name": "Remington Schinner",
      "jobTitle": "Teacher",
      "phoneNumber": "07957 036 118",
      "organisation": {
        "name": "Conroy - Champlin School",
        "address": {
          "line1": "1 The Avenue",
          "town": "London",
          "postcode": "W9 1ST"
        }
      }
    },
    "teacher": {
      "firstName": "Jackson",
      "lastName": "Mohr",
      "hasAnotherName": "I do not know",
      "dateOfBirth": "2022-02-16T18:12:18.571Z",
      "hasNationalInsuranceNumber": "No",
      "hasTeacherReferenceNumber": "No",
      "hasQTS": "No",
      "hasEmailAddress": "No",
      "hasPhoneNumber": "No",
      "address": {
        "line1": "1 The Walk",
        "town": "Manchester",
        "postcode": "M1 1AG"
      },
      "hasJobStartDate": "Yes",
      "jobStartDate": "2022-01-30T01:03:27.547Z",
      "areTheyStillEmployed": "Yes",
      "jobTitle": "Headteacher",
      "doesWorkAtSameOrganisation": "No",
      "organisation": {
        "name": "Murphy, Funk and Satterfield School",
        "address": {
          "line1": "1 The Avenue",
          "town": "London",
          "postcode": "W9 1ST"
        }
      },
      "roleDescriptionMethod": "I’ll upload a job description",
      "roleDescriptionFile": {
        "name": "job-description.pdf",
        "size": "1MB"
      },
      "isTeachingSomewhereElse": "No, they’re not teaching somewhere else"
    },
    "allegation": {
      "method": "I’ll do this later",
      "hasToldDBS": "Yes, I’ve told DBS"
    },
    "previousAllegations": {
      "hasPreviousAllegations": "I do not know"
    },
    "evidence": {
      "hasEvidence": "No"
    }
  },
  {
    "id": "862904",
    "referralDate": "2022-03-19T20:10:01.736Z",
    "referrer": {
      "name": "Saige Roberts",
      "jobTitle": "Teacher",
      "phoneNumber": "07945 970 497",
      "organisation": {
        "name": "Boehm, Pagac and Jones School",
        "address": {
          "line1": "1 The Avenue",
          "town": "London",
          "postcode": "W9 1ST"
        }
      }
    },
    "teacher": {
      "firstName": "Camryn",
      "lastName": "Trantow",
      "hasAnotherName": "Yes",
      "otherName": "Bobsky",
      "dateOfBirth": "2022-10-08T14:22:17.850Z",
      "hasNationalInsuranceNumber": "Yes",
      "nationalInsuranceNumber": "QQ 12 34 56 C",
      "hasTeacherReferenceNumber": "No",
      "hasQTS": "No",
      "hasEmailAddress": "Yes",
      "emailAddress": "camryn.trantow@gmail.com",
      "hasPhoneNumber": "Yes",
      "phoneNumber": "07993 474 591",
      "address": {
        "line1": "1 The Walk",
        "town": "Manchester",
        "postcode": "M1 1AG"
      },
      "hasJobStartDate": "Yes",
      "jobStartDate": "2022-08-11T19:52:18.875Z",
      "areTheyStillEmployed": "Yes",
      "jobTitle": "Teaching assistant",
      "doesWorkAtSameOrganisation": "No",
      "organisation": {
        "name": "Wiegand, Pagac and Schmeler School",
        "address": {
          "line1": "1 The Avenue",
          "town": "London",
          "postcode": "W9 1ST"
        }
      },
      "roleDescriptionMethod": "I’ll do this later",
      "isTeachingSomewhereElse": "I do not know"
    },
    "allegation": {
      "method": "I’ll upload the allegation details",
      "file": {
        "name": "allegation-details.pdf",
        "size": "2MB"
      },
      "hasToldDBS": "No"
    },
    "previousAllegations": {
      "hasPreviousAllegations": "No"
    },
    "evidence": {
      "hasEvidence": "No"
    }
  },
  {
    "id": "799154",
    "referralDate": "2022-04-21T14:14:27.621Z",
    "referrer": {
      "name": "Jany Goodwin",
      "jobTitle": "Headteacher",
      "phoneNumber": "07919 084 956",
      "organisation": {
        "name": "Ullrich LLC School",
        "address": {
          "line1": "1 The Avenue",
          "town": "London",
          "postcode": "W9 1ST"
        }
      }
    },
    "teacher": {
      "firstName": "Lina",
      "lastName": "Dickinson",
      "hasAnotherName": "No",
      "dateOfBirth": "2022-09-29T05:22:25.577Z",
      "hasNationalInsuranceNumber": "No",
      "hasTeacherReferenceNumber": "Yes",
      "trn": "4567814",
      "hasQTS": "Yes",
      "hasEmailAddress": "No",
      "hasPhoneNumber": "Yes",
      "phoneNumber": "07990 293 142",
      "address": {
        "line1": "1 The Walk",
        "town": "Manchester",
        "postcode": "M1 1AG"
      },
      "hasJobStartDate": "No",
      "areTheyStillEmployed": "Yes",
      "jobTitle": "Headteacher",
      "doesWorkAtSameOrganisation": "Yes",
      "roleDescriptionMethod": "I’ll upload a job description",
      "roleDescriptionFile": {
        "name": "job-description.pdf",
        "size": "1MB"
      },
      "isTeachingSomewhereElse": "I do not know"
    },
    "allegation": {
      "method": "I’ll do this later",
      "hasToldDBS": "Yes, I’ve told DBS"
    },
    "previousAllegations": {
      "hasPreviousAllegations": "Yes",
      "method": "I’ll give details of the previous misconduct",
      "description": "Similique incidunt aperiam. Blanditiis enim modi totam fugit est pariatur aliquam. A debitis minima adipisci nihil eveniet iste eos minima.\n\nCorrupti totam itaque voluptatibus. Consequuntur voluptatum ducimus reprehenderit tempora vitae. Deleniti eveniet corrupti veritatis doloribus ea voluptatem totam doloremque. Labore a molestias ducimus molestiae excepturi neque dicta in.\n\nAdipisci earum dolores harum dolores pariatur sed doloremque incidunt necessitatibus. Voluptate consectetur dolores rem dolorem aperiam mollitia. Officiis suscipit vitae at beatae voluptatum minima beatae distinctio debitis. Corrupti temporibus facere reiciendis pariatur possimus."
    },
    "evidence": {
      "hasEvidence": "No"
    }
  }
]